justfunc/__init__.py
justfunc/interpreter.py
just_func-0.0.1.dist-info/LICENSE
just_func-0.0.1.dist-info/METADATA
just_func-0.0.1.dist-info/WHEEL
just_func-0.0.1.dist-info/top_level.txt
just_func-0.0.1.dist-info/RECORD
