Metadata-Version: 2.1
Name: just-func
Version: 0.0.1
Summary: A python interpreter for the just-func language
Home-page: https://github.com/justland/just-func-python
Author: Vincent White
Author-email: xstrengthofonex@gmail.com
License: UNKNOWN
Platform: UNKNOWN
